CHANGES.txt
LICENSE
MANIFEST.in
README.md
README.txt
setup.py
src/ibmiotc/__init__.py
src/ibmiotc/application.py
src/ibmiotc/device.py
src/ibmiotc.egg-info/PKG-INFO
src/ibmiotc.egg-info/SOURCES.txt
src/ibmiotc.egg-info/dependency_links.txt
src/ibmiotc.egg-info/requires.txt
src/ibmiotc.egg-info/top_level.txt