Metadata-Version: 1.0
Name: ibmiotc
Version: 0.0.7
Summary: IBM Internet of Things Cloud for Python
Home-page: https://github.com/ibm-messaging/iot-python
Author: David Parker
Author-email: parkerda@uk.ibm.com
License: Eclipse Public License - v 1.0
